datasette_block_robots/__init__.py
datasette_block_robots/hookspecs.py
datasette_block_robots-1.1.dist-info/METADATA
datasette_block_robots-1.1.dist-info/WHEEL
datasette_block_robots-1.1.dist-info/entry_points.txt
datasette_block_robots-1.1.dist-info/top_level.txt
datasette_block_robots-1.1.dist-info/RECORD
