Metadata-Version: 2.1
Name: datasette-block-robots
Version: 1.1
Summary: Datasette plugin that blocks all robots using robots.txt
Home-page: https://github.com/simonw/datasette-block-robots
Author: Simon Willison
License: Apache License, Version 2.0
Project-URL: Issues, https://github.com/simonw/datasette-block-robots/issues
Project-URL: CI, https://github.com/simonw/datasette-block-robots/actions
Project-URL: Changelog, https://github.com/simonw/datasette-block-robots/releases
Platform: UNKNOWN
Requires-Dist: datasette (>=0.50)
Provides-Extra: test
Requires-Dist: pytest ; extra == 'test'
Requires-Dist: pytest-asyncio ; extra == 'test'
Requires-Dist: httpx ; extra == 'test'
